parsyfiles/__init__.py
parsyfiles/converting_core.py
parsyfiles/filesystem_mapping.py
parsyfiles/global_config.py
parsyfiles/log_utils.py
parsyfiles/parsing_combining_parsers.py
parsyfiles/parsing_core.py
parsyfiles/parsing_core_api.py
parsyfiles/parsing_fw.py
parsyfiles/parsing_registries.py
parsyfiles/type_inspection_tools.py
parsyfiles/var_checker.py
parsyfiles/plugins_base/__init__.py
parsyfiles/plugins_base/support_for_collections.py
parsyfiles/plugins_base/support_for_configparser.py
parsyfiles/plugins_base/support_for_objects.py
parsyfiles/plugins_base/support_for_primitive_types.py
parsyfiles/plugins_optional/__init__.py
parsyfiles/plugins_optional/support_for_attrs.py
parsyfiles/plugins_optional/support_for_jprops.py
parsyfiles/plugins_optional/support_for_numpy.py
parsyfiles/plugins_optional/support_for_pandas.py
parsyfiles/plugins_optional/support_for_yaml.py
parsyfiles/tests/__init__.py
parsyfiles/tests/conftest.py
parsyfiles/tests/parsing_capabilities_by_type/__init__.py
parsyfiles/tests/parsing_capabilities_by_type/test_parse_collections.py
parsyfiles/tests/parsing_capabilities_by_type/test_parse_custom_object.py
parsyfiles/tests/parsing_capabilities_by_type/test_parse_primitives.py
parsyfiles/tests/parsing_capabilities_by_type/test_parse_typevars.py
parsyfiles/tests/parsing_capabilities_by_type/test_parse_unions.py
parsyfiles-2.9.1.dist-info/DESCRIPTION.rst
parsyfiles-2.9.1.dist-info/METADATA
parsyfiles-2.9.1.dist-info/RECORD
parsyfiles-2.9.1.dist-info/WHEEL
parsyfiles-2.9.1.dist-info/metadata.json
parsyfiles-2.9.1.dist-info/top_level.txt
