Metadata-Version: 2.0
Name: parsyfiles
Version: 2.9.1
Summary: Combines most popular python parsers (json, jprops, pickle...) with user-defined parsers and type converters to read objects from files. Supports multifile & multiparser objects, typically useful to organize test data. Leverages PEP484 type hints in order to intelligently use the best parser/converter chain, and to try several combinations if relevant
Home-page: https://github.com/smarie/parsyfiles
Author: Sylvain Marié
Author-email: sylvain.marie@schneider-electric.com
License: BSD 3-Clause
Download-URL: https://github.com/smarie/parsyfiles/tarball/2.9.1
Keywords: parsing framework file converter conversion parser object folder dict yaml propertiescollection complex simple benchmark type class PEP484 type-hint data binding
Platform: UNKNOWN
Classifier: Development Status :: 5 - Production/Stable
Classifier: Intended Audience :: Developers
Classifier: Topic :: Software Development :: Libraries :: Python Modules
Classifier: License :: OSI Approved :: BSD License
Classifier: Programming Language :: Python :: 3.5
Obsoletes: sficopaf
Requires-Dist: typing-inspect
Requires-Dist: pytypes
Provides-Extra: autoclass
Requires-Dist: autoclass; extra == 'autoclass'
Provides-Extra: jprops_parser
Requires-Dist: jprops; extra == 'jprops_parser'
Provides-Extra: numpy_parser
Requires-Dist: numpy; extra == 'numpy_parser'
Provides-Extra: pandas_parser
Requires-Dist: numpy; extra == 'pandas_parser'
Requires-Dist: pandas; extra == 'pandas_parser'
Provides-Extra: xls_parser
Requires-Dist: xlrd; extra == 'xls_parser'
Provides-Extra: yaml_parser
Requires-Dist: pyyaml; extra == 'yaml_parser'
